hyperdrive/Algotrader.py
hyperdrive/Broker.py
hyperdrive/Calculus.py
hyperdrive/Constants.py
hyperdrive/Crypt.py
hyperdrive/DataSource.py
hyperdrive/Exchange.py
hyperdrive/FileOps.py
hyperdrive/History.py
hyperdrive/Precognition.py
hyperdrive/Storage.py
hyperdrive/TimeMachine.py
hyperdrive/Transformer.py
hyperdrive/Utils.py
hyperdrive/Workflow.py
hyperdrive/__init__.py
hyperdrive-1.15.3.dist-info/LICENSE
hyperdrive-1.15.3.dist-info/METADATA
hyperdrive-1.15.3.dist-info/WHEEL
hyperdrive-1.15.3.dist-info/top_level.txt
hyperdrive-1.15.3.dist-info/RECORD
