Metadata-Version: 2.1
Name: hyperdrive
Version: 1.15.3
Summary: An algorithmic trading platform
Home-page: https://github.com/suchak1/hyperdrive
Author: Krish Suchak
Author-email: suchak.krish@gmail.com
Project-URL: Bug Reports, https://github.com/suchak1/hyperdrive/issues
Project-URL: Source, https://github.com/suchak1/hyperdrive
Requires-Python: >=3.7
License-File: LICENSE
Requires-Dist: python-dotenv==1.1.0
Requires-Dist: pandas==2.2.3
Requires-Dist: robin-stocks==3.4.0
Requires-Dist: boto3==1.38.13
Requires-Dist: polygon-api-client==1.11.0
Requires-Dist: pytz==2025.2
Requires-Dist: vectorbt==0.27.3
Requires-Dist: scipy==1.15.3
Requires-Dist: scikit-learn==1.6.1
Requires-Dist: cryptography==44.0.3
Requires-Dist: ta==0.11.0
Requires-Dist: python-binance==1.0.28
Requires-Dist: imbalanced-learn==0.13.0
Requires-Dist: icosphere==0.1.3
Requires-Dist: numpy==1.26.4
Requires-Dist: beautifulsoup4==4.13.4
Requires-Dist: lxml==5.4.0
Requires-Dist: autogluon==1.3.0
Requires-Dist: selenium
